fine_python_module_exports/__init__.py
fine_python_module_exports/api.py
fine_python_module_exports/extension.py
fine_python_module_exports/py.typed
fine_python_module_exports-0.2.0.dist-info/METADATA
fine_python_module_exports-0.2.0.dist-info/WHEEL
fine_python_module_exports-0.2.0.dist-info/top_level.txt
fine_python_module_exports-0.2.0.dist-info/RECORD
