Metadata-Version: 2.4
Name: fine-python-module-exports
Version: 0.2.0
Author-email: Vladyslav Hnatiuk <aders1234@gmail.com>
Requires-Python: <3.14,>=3.11
Requires-Dist: finecode_extension_api==0.3.*
Requires-Dist: fine_python_ast==0.2.*
